fedfair/__init__.py
fedfair-0.0.1a0.dist-info/LICENSE
fedfair-0.0.1a0.dist-info/METADATA
fedfair-0.0.1a0.dist-info/WHEEL
fedfair-0.0.1a0.dist-info/top_level.txt
fedfair-0.0.1a0.dist-info/RECORD
